aionetbox/__init__.py
aionetbox/api.py
aionetbox/exceptions.py
aionetbox/mock.py
aionetbox/utils.py
tests/__init__.py
tests/fixtures.py
tests/test_api.py
tests/test_utils.py
aionetbox-1.7.4.dist-info/LICENSE
aionetbox-1.7.4.dist-info/METADATA
aionetbox-1.7.4.dist-info/WHEEL
aionetbox-1.7.4.dist-info/top_level.txt
aionetbox-1.7.4.dist-info/RECORD
