Metadata-Version: 2.1
Name: aionetbox
Version: 1.7.4
Summary: Async netbox library
Home-page: https://github.com/vapor-ware/aionetbox
Author: Marco Ceppi
Author-email: marco@vapor.io
License: GNU General Public License v3.0
Classifier: Programming Language :: Python :: 3
Classifier: License :: OSI Approved :: GNU General Public License v3 (GPLv3)
Classifier: Operating System :: OS Independent
Requires-Python: >=3.6
License-File: LICENSE
Requires-Dist: aiohttp[speedups] <4.0
Requires-Dist: prance[osv]
Provides-Extra: icu
Requires-Dist: prance[icu,osv] ; extra == 'icu'
